[null,{"id":1,"actions":[{"skillId":1,"rating":5,"conditionType":0,"conditionParam1":0,"conditionParam2":0}],"battlerHue":0,"battlerName":"SF_Slaughterrobot","dropItems":[{"kind":2,"dataId":5,"denominator":1},{"kind":1,"dataId":7,"denominator":1},{"kind":3,"dataId":28,"denominator":1}],"exp":200,"traits":[{"code":22,"dataId":0,"value":0.95},{"code":22,"dataId":1,"value":0.05},{"code":31,"dataId":1,"value":0}],"gold":10,"name":"Goblin","note":"","params":[10,999,20,20,20,20,20,20]},{"id":2,"actions":[{"conditionParam1":0,"conditionParam2":0,"conditionType":0,"rating":5,"skillId":1},{"skillId":23,"rating":3,"conditionType":1,"conditionParam1":0,"conditionParam2":2}],"battlerHue":0,"battlerName":"Gnome","dropItems":[{"dataId":1,"denominator":1,"kind":0},{"dataId":1,"denominator":1,"kind":0},{"dataId":1,"denominator":1,"kind":0}],"exp":10,"traits":[{"code":22,"dataId":0,"value":0.95},{"code":22,"dataId":1,"value":0.05},{"code":31,"dataId":1,"value":0}],"gold":8,"name":"Gnome","note":"","params":[250,0,20,25,20,20,20,20]},{"id":3,"actions":[{"conditionParam1":0,"conditionParam2":0,"conditionType":0,"rating":5,"skillId":1}],"battlerHue":0,"battlerName":"Crow","dropItems":[{"dataId":1,"denominator":1,"kind":0},{"dataId":1,"denominator":1,"kind":0},{"dataId":1,"denominator":1,"kind":0}],"exp":15,"traits":[{"code":22,"dataId":0,"value":0.95},{"code":22,"dataId":1,"value":0.1},{"code":31,"dataId":1,"value":0}],"gold":8,"name":"Crow","note":"","params":[250,50,25,20,20,20,25,20]},{"id":4,"actions":[{"conditionParam1":0,"conditionParam2":0,"conditionType":0,"rating":5,"skillId":1},{"skillId":52,"rating":4,"conditionType":2,"conditionParam1":0,"conditionParam2":0.3}],"battlerHue":0,"battlerName":"Treant","dropItems":[{"dataId":1,"denominator":1,"kind":0},{"dataId":1,"denominator":1,"kind":0},{"dataId":1,"denominator":1,"kind":0}],"exp":30,"traits":[{"code":22,"dataId":0,"value":0.95},{"code":22,"dataId":1,"value":0.05},{"code":31,"dataId":1,"value":0},{"code":11,"dataId":2,"value":2}],"gold":15,"name":"Torrent","note":"<BreakVal: 500>","params":[500,50,30,20,30,30,30,30]},{"id":5,"actions":[{"conditionParam1":0,"conditionParam2":0,"conditionType":0,"rating":5,"skillId":1},{"skillId":99,"rating":4,"conditionType":1,"conditionParam1":0,"conditionParam2":2},{"skillId":13,"rating":6,"conditionType":2,"conditionParam1":0,"conditionParam2":0.3}],"battlerHue":0,"battlerName":"Hi_monster","dropItems":[{"dataId":1,"denominator":1,"kind":0},{"dataId":1,"denominator":1,"kind":0},{"dataId":1,"denominator":1,"kind":0}],"exp":100,"traits":[{"code":22,"dataId":0,"value":0.95},{"code":22,"dataId":1,"value":0.05},{"code":31,"dataId":1,"value":0},{"code":63,"dataId":1,"value":1}],"gold":50,"name":"Beast","note":"","params":[1000,50,40,20,40,40,40,40]},{"id":6,"actions":[{"conditionParam1":0,"conditionParam2":0,"conditionType":0,"rating":5,"skillId":1}],"battlerHue":0,"battlerName":"","dropItems":[{"dataId":1,"denominator":1,"kind":0},{"dataId":1,"denominator":1,"kind":0},{"dataId":1,"denominator":1,"kind":0}],"exp":0,"traits":[{"code":22,"dataId":0,"value":0.95},{"code":22,"dataId":1,"value":0.05},{"code":31,"dataId":1,"value":0}],"gold":0,"name":"","note":"","params":[100,0,10,10,10,10,10,10]},{"id":7,"actions":[{"conditionParam1":0,"conditionParam2":0,"conditionType":0,"rating":5,"skillId":1}],"battlerHue":0,"battlerName":"","dropItems":[{"dataId":1,"denominator":1,"kind":0},{"dataId":1,"denominator":1,"kind":0},{"dataId":1,"denominator":1,"kind":0}],"exp":0,"traits":[{"code":22,"dataId":0,"value":0.95},{"code":22,"dataId":1,"value":0.05},{"code":31,"dataId":1,"value":0}],"gold":0,"name":"","note":"","params":[100,0,10,10,10,10,10,10]},{"id":8,"actions":[{"conditionParam1":0,"conditionParam2":0,"conditionType":0,"rating":5,"skillId":1}],"battlerHue":0,"battlerName":"","dropItems":[{"dataId":1,"denominator":1,"kind":0},{"dataId":1,"denominator":1,"kind":0},{"dataId":1,"denominator":1,"kind":0}],"exp":0,"traits":[{"code":22,"dataId":0,"value":0.95},{"code":22,"dataId":1,"value":0.05},{"code":31,"dataId":1,"value":0}],"gold":0,"name":"","note":"","params":[100,0,10,10,10,10,10,10]},{"id":9,"actions":[{"conditionParam1":0,"conditionParam2":0,"conditionType":0,"rating":5,"skillId":1}],"battlerHue":0,"battlerName":"","dropItems":[{"dataId":1,"denominator":1,"kind":0},{"dataId":1,"denominator":1,"kind":0},{"dataId":1,"denominator":1,"kind":0}],"exp":0,"traits":[{"code":22,"dataId":0,"value":0.95},{"code":22,"dataId":1,"value":0.05},{"code":31,"dataId":1,"value":0}],"gold":0,"name":"","note":"","params":[100,0,10,10,10,10,10,10]},{"id":10,"actions":[{"conditionParam1":0,"conditionParam2":0,"conditionType":0,"rating":5,"skillId":1}],"battlerHue":0,"battlerName":"","dropItems":[{"dataId":1,"denominator":1,"kind":0},{"dataId":1,"denominator":1,"kind":0},{"dataId":1,"denominator":1,"kind":0}],"exp":0,"traits":[{"code":22,"dataId":0,"value":0.95},{"code":22,"dataId":1,"value":0.05},{"code":31,"dataId":1,"value":0}],"gold":0,"name":"","note":"","params":[100,0,10,10,10,10,10,10]},{"id":11,"actions":[{"skillId":1,"rating":1,"conditionType":0,"conditionParam1":0,"conditionParam2":0},{"skillId":4,"rating":5,"conditionType":0,"conditionParam1":0,"conditionParam2":0}],"battlerHue":0,"battlerName":"mondama","dropItems":[{"dataId":1,"denominator":1,"kind":0},{"dataId":1,"denominator":1,"kind":0},{"dataId":1,"denominator":1,"kind":0}],"exp":26,"traits":[{"code":22,"dataId":0,"value":0},{"code":31,"dataId":1,"value":0}],"gold":18,"name":"Grotesque Monster","note":"","params":[30,0,1,6,6,6,21,1]},{"id":12,"actions":[{"skillId":1,"rating":1,"conditionType":0,"conditionParam1":0,"conditionParam2":0},{"skillId":4,"rating":5,"conditionType":0,"conditionParam1":0,"conditionParam2":0}],"battlerHue":0,"battlerName":"mondama","dropItems":[{"kind":1,"dataId":352,"denominator":2},{"kind":1,"dataId":353,"denominator":4},{"dataId":1,"denominator":1,"kind":0}],"exp":26,"traits":[{"code":22,"dataId":0,"value":0.95},{"code":31,"dataId":1,"value":0}],"gold":18,"name":"Grotesque Monster","note":"","params":[30,0,20,6,6,6,23,1]},{"id":13,"actions":[{"conditionParam1":0,"conditionParam2":0,"conditionType":0,"rating":5,"skillId":1}],"battlerHue":0,"battlerName":"","dropItems":[{"dataId":1,"denominator":1,"kind":0},{"dataId":1,"denominator":1,"kind":0},{"dataId":1,"denominator":1,"kind":0}],"exp":0,"traits":[{"code":22,"dataId":0,"value":0.95},{"code":22,"dataId":1,"value":0.05},{"code":31,"dataId":1,"value":0}],"gold":0,"name":"","note":"","params":[100,0,10,10,10,10,10,10]},{"id":14,"actions":[{"skillId":1,"rating":1,"conditionType":0,"conditionParam1":0,"conditionParam2":0},{"skillId":152,"rating":1,"conditionType":0,"conditionParam1":0,"conditionParam2":0},{"skillId":152,"rating":3,"conditionType":1,"conditionParam1":2,"conditionParam2":3},{"skillId":151,"rating":3,"conditionType":1,"conditionParam1":3,"conditionParam2":3},{"skillId":153,"rating":6,"conditionType":2,"conditionParam1":0,"conditionParam2":0.7},{"skillId":157,"rating":9,"conditionType":6,"conditionParam1":582,"conditionParam2":0},{"skillId":154,"rating":9,"conditionType":6,"conditionParam1":583,"conditionParam2":0}],"battlerHue":0,"battlerName":"05_t","dropItems":[{"dataId":1,"denominator":1,"kind":0},{"dataId":1,"denominator":1,"kind":0},{"dataId":1,"denominator":1,"kind":0}],"exp":51,"traits":[{"code":22,"dataId":0,"value":0.95},{"code":31,"dataId":1,"value":0},{"code":23,"dataId":4,"value":0}],"gold":22,"name":"Huge Slime","note":"<BreakVal: 150>\n<BreakDuration: 5>","params":[1000,0,36,6,6,6,22,1]},{"id":15,"actions":[{"conditionParam1":0,"conditionParam2":0,"conditionType":0,"rating":5,"skillId":1}],"battlerHue":0,"battlerName":"","dropItems":[{"dataId":1,"denominator":1,"kind":0},{"dataId":1,"denominator":1,"kind":0},{"dataId":1,"denominator":1,"kind":0}],"exp":0,"traits":[{"code":22,"dataId":0,"value":0.95},{"code":22,"dataId":1,"value":0.05},{"code":31,"dataId":1,"value":0}],"gold":0,"name":"","note":"","params":[100,0,10,10,10,10,10,10]},{"id":16,"actions":[{"skillId":1,"rating":1,"conditionType":0,"conditionParam1":0,"conditionParam2":0},{"skillId":4,"rating":5,"conditionType":0,"conditionParam1":0,"conditionParam2":0},{"skillId":155,"rating":4,"conditionType":0,"conditionParam1":0,"conditionParam2":0},{"skillId":156,"rating":5,"conditionType":0,"conditionParam1":0,"conditionParam2":0}],"battlerHue":0,"battlerName":"VXred","dropItems":[{"dataId":1,"denominator":1,"kind":0},{"dataId":1,"denominator":1,"kind":0},{"dataId":1,"denominator":1,"kind":0}],"exp":56,"traits":[{"code":22,"dataId":0,"value":0.95},{"code":31,"dataId":1,"value":0}],"gold":20,"name":"Heat Beast","note":"","params":[60,0,25,10,6,6,23,1]},{"id":17,"actions":[{"skillId":1,"rating":1,"conditionType":0,"conditionParam1":0,"conditionParam2":0},{"skillId":158,"rating":5,"conditionType":0,"conditionParam1":0,"conditionParam2":0},{"skillId":156,"rating":5,"conditionType":0,"conditionParam1":0,"conditionParam2":0},{"skillId":157,"rating":4,"conditionType":2,"conditionParam1":0.75,"conditionParam2":1}],"battlerHue":0,"battlerName":"SF_Wolf","dropItems":[{"dataId":1,"denominator":1,"kind":0},{"dataId":1,"denominator":1,"kind":0},{"dataId":1,"denominator":1,"kind":0}],"exp":89,"traits":[{"code":22,"dataId":0,"value":0.95},{"code":31,"dataId":1,"value":0}],"gold":22,"name":"Lone Wolf","note":"","params":[150,0,34,34,6,6,28,1]},{"id":18,"actions":[{"skillId":1,"rating":1,"conditionType":0,"conditionParam1":0,"conditionParam2":0},{"skillId":158,"rating":5,"conditionType":0,"conditionParam1":0,"conditionParam2":0},{"skillId":159,"rating":9,"conditionType":1,"conditionParam1":2,"conditionParam2":3},{"skillId":160,"rating":9,"conditionType":1,"conditionParam1":3,"conditionParam2":3}],"battlerHue":0,"battlerName":"Tigerbunny","dropItems":[{"dataId":1,"denominator":1,"kind":0},{"dataId":1,"denominator":1,"kind":0},{"dataId":1,"denominator":1,"kind":0}],"exp":180,"traits":[{"code":22,"dataId":0,"value":0.95},{"code":31,"dataId":1,"value":0}],"gold":40,"name":"Tiger Bunny","note":"","params":[240,0,40,38,6,6,30,1]},{"id":19,"actions":[{"skillId":1,"rating":1,"conditionType":0,"conditionParam1":0,"conditionParam2":0},{"skillId":4,"rating":5,"conditionType":0,"conditionParam1":0,"conditionParam2":0},{"skillId":156,"rating":5,"conditionType":0,"conditionParam1":0,"conditionParam2":0}],"battlerHue":0,"battlerName":"09_p","dropItems":[{"dataId":1,"denominator":1,"kind":0},{"dataId":1,"denominator":1,"kind":0},{"dataId":1,"denominator":1,"kind":0}],"exp":133,"traits":[{"code":22,"dataId":0,"value":0.95},{"code":31,"dataId":1,"value":0},{"code":11,"dataId":2,"value":1.5}],"gold":30,"name":"Tuber","note":"","params":[175,0,36,45,6,6,26,1]},{"id":20,"actions":[{"skillId":1,"rating":1,"conditionType":0,"conditionParam1":0,"conditionParam2":0},{"skillId":4,"rating":5,"conditionType":0,"conditionParam1":0,"conditionParam2":0},{"skillId":156,"rating":5,"conditionType":0,"conditionParam1":0,"conditionParam2":0}],"battlerHue":0,"battlerName":"10_p","dropItems":[{"dataId":1,"denominator":1,"kind":0},{"dataId":1,"denominator":1,"kind":0},{"dataId":1,"denominator":1,"kind":0}],"exp":555,"traits":[{"code":22,"dataId":0,"value":0.95},{"code":31,"dataId":1,"value":0},{"code":11,"dataId":2,"value":1.5}],"gold":333,"name":"Treant","note":"<BreakVal: 333>\n<BreakDuration: 4>","params":[999,0,48,58,6,6,30,1]},{"id":21,"actions":[{"skillId":1,"rating":1,"conditionType":0,"conditionParam1":0,"conditionParam2":0},{"skillId":161,"rating":3,"conditionType":0,"conditionParam1":0,"conditionParam2":0},{"skillId":163,"rating":2,"conditionType":1,"conditionParam1":2,"conditionParam2":5},{"skillId":162,"rating":9,"conditionType":6,"conditionParam1":584,"conditionParam2":0},{"skillId":165,"rating":6,"conditionType":6,"conditionParam1":585,"conditionParam2":0},{"skillId":164,"rating":9,"conditionType":6,"conditionParam1":586,"conditionParam2":0},{"skillId":166,"rating":6,"conditionType":6,"conditionParam1":587,"conditionParam2":0},{"skillId":167,"rating":6,"conditionType":6,"conditionParam1":588,"conditionParam2":0},{"skillId":168,"rating":6,"conditionType":6,"conditionParam1":589,"conditionParam2":0}],"battlerHue":0,"battlerName":"05_t","dropItems":[{"dataId":1,"denominator":1,"kind":0},{"dataId":1,"denominator":1,"kind":0},{"dataId":1,"denominator":1,"kind":0}],"exp":340,"traits":[{"code":22,"dataId":0,"value":0.95},{"code":31,"dataId":1,"value":0},{"code":23,"dataId":4,"value":0}],"gold":110,"name":"Spring Monster","note":"<BreakVal: 75>\n<BreakDuration: 8>","params":[350,0,34,15,6,6,30,1]},{"id":22,"actions":[{"skillId":1,"rating":1,"conditionType":0,"conditionParam1":0,"conditionParam2":0},{"skillId":169,"rating":5,"conditionType":0,"conditionParam1":0,"conditionParam2":0},{"skillId":170,"rating":5,"conditionType":0,"conditionParam1":0,"conditionParam2":0},{"skillId":171,"rating":6,"conditionType":1,"conditionParam1":2,"conditionParam2":4}],"battlerHue":0,"battlerName":"doll_s1","dropItems":[{"kind":1,"dataId":352,"denominator":1},{"kind":1,"dataId":353,"denominator":1},{"kind":1,"dataId":354,"denominator":1}],"exp":280,"traits":[{"code":22,"dataId":0,"value":0.95},{"code":31,"dataId":1,"value":0}],"gold":53,"name":"Magic Doll Type-P","note":"<BreakVal: 75>\n<BreakDuration: 3>","params":[350,0,46,50,6,6,35,1]},{"id":23,"actions":[{"skillId":1,"rating":1,"conditionType":0,"conditionParam1":0,"conditionParam2":0},{"skillId":169,"rating":5,"conditionType":0,"conditionParam1":0,"conditionParam2":0},{"skillId":170,"rating":5,"conditionType":0,"conditionParam1":0,"conditionParam2":0},{"skillId":171,"rating":6,"conditionType":1,"conditionParam1":2,"conditionParam2":4}],"battlerHue":0,"battlerName":"ad_Golem2","dropItems":[{"kind":1,"dataId":364,"denominator":2},{"kind":1,"dataId":364,"denominator":4},{"dataId":1,"denominator":1,"kind":0}],"exp":360,"traits":[{"code":22,"dataId":0,"value":0.95},{"code":31,"dataId":1,"value":0}],"gold":150,"name":"Sand Magic Doll","note":"<BreakVal: 120>\n<BreakDuration: 4>","params":[400,0,56,80,6,6,35,1]},{"id":24,"actions":[{"skillId":1,"rating":1,"conditionType":0,"conditionParam1":0,"conditionParam2":0},{"skillId":169,"rating":5,"conditionType":0,"conditionParam1":0,"conditionParam2":0},{"skillId":170,"rating":5,"conditionType":0,"conditionParam1":0,"conditionParam2":0},{"skillId":171,"rating":6,"conditionType":1,"conditionParam1":2,"conditionParam2":4}],"battlerHue":0,"battlerName":"ad_Golem","dropItems":[{"kind":1,"dataId":364,"denominator":1},{"kind":0,"dataId":0,"denominator":1},{"dataId":1,"denominator":1,"kind":0}],"exp":780,"traits":[{"code":22,"dataId":0,"value":0.95},{"code":31,"dataId":1,"value":0}],"gold":360,"name":"Gold Dust Magic Doll","note":"<BreakVal: 120>\n<BreakDuration: 4>","params":[600,0,62,80,6,6,35,1]},{"id":25,"actions":[{"skillId":1,"rating":1,"conditionType":0,"conditionParam1":0,"conditionParam2":0},{"skillId":170,"rating":5,"conditionType":0,"conditionParam1":0,"conditionParam2":0},{"skillId":171,"rating":6,"conditionType":1,"conditionParam1":2,"conditionParam2":4},{"skillId":102,"rating":4,"conditionType":0,"conditionParam1":0,"conditionParam2":0}],"battlerHue":0,"battlerName":"ad_golem3","dropItems":[{"kind":1,"dataId":364,"denominator":1},{"kind":1,"dataId":364,"denominator":1},{"dataId":1,"denominator":1,"kind":0}],"exp":2000,"traits":[{"code":22,"dataId":0,"value":0.9},{"code":31,"dataId":1,"value":0}],"gold":2000,"name":"Stone Magic Doll","note":"<BreakVal: 350>\n<BreakDuration: 4>","params":[888,0,80,130,6,6,28,1]},{"id":26,"actions":[{"skillId":1,"rating":1,"conditionType":0,"conditionParam1":0,"conditionParam2":0},{"skillId":4,"rating":5,"conditionType":0,"conditionParam1":0,"conditionParam2":0},{"skillId":172,"rating":9,"conditionType":1,"conditionParam1":1,"conditionParam2":0},{"skillId":157,"rating":4,"conditionType":0,"conditionParam1":0,"conditionParam2":0},{"skillId":173,"rating":5,"conditionType":0,"conditionParam1":0,"conditionParam2":0}],"battlerHue":0,"battlerName":"ETNR_008","dropItems":[{"dataId":1,"denominator":1,"kind":0},{"dataId":1,"denominator":1,"kind":0},{"dataId":1,"denominator":1,"kind":0}],"exp":290,"traits":[{"code":22,"dataId":0,"value":0.95},{"code":31,"dataId":1,"value":0}],"gold":130,"name":"Sandworm","note":"","params":[200,0,43,30,6,6,32,1]},{"id":27,"actions":[{"skillId":1,"rating":1,"conditionType":0,"conditionParam1":0,"conditionParam2":0},{"skillId":4,"rating":5,"conditionType":0,"conditionParam1":0,"conditionParam2":0},{"skillId":175,"rating":5,"conditionType":0,"conditionParam1":0,"conditionParam2":0}],"battlerHue":0,"battlerName":"alfa_mu","dropItems":[{"dataId":1,"denominator":1,"kind":0},{"dataId":1,"denominator":1,"kind":0},{"dataId":1,"denominator":1,"kind":0}],"exp":96,"traits":[{"code":22,"dataId":0,"value":0.95},{"code":31,"dataId":1,"value":0},{"code":11,"dataId":2,"value":1.5}],"gold":30,"name":"α Mucus","note":"","params":[120,0,43,30,6,6,27,1]},{"id":28,"actions":[{"skillId":1,"rating":1,"conditionType":0,"conditionParam1":0,"conditionParam2":0},{"skillId":4,"rating":5,"conditionType":0,"conditionParam1":0,"conditionParam2":0},{"skillId":176,"rating":5,"conditionType":0,"conditionParam1":0,"conditionParam2":0}],"battlerHue":0,"battlerName":"beta_mu","dropItems":[{"dataId":1,"denominator":1,"kind":0},{"dataId":1,"denominator":1,"kind":0},{"dataId":1,"denominator":1,"kind":0}],"exp":96,"traits":[{"code":22,"dataId":0,"value":0.95},{"code":31,"dataId":1,"value":0},{"code":11,"dataId":2,"value":1.5}],"gold":30,"name":"β Mucus","note":"","params":[120,0,43,30,6,6,27,1]},{"id":29,"actions":[{"skillId":1,"rating":1,"conditionType":0,"conditionParam1":0,"conditionParam2":0},{"skillId":169,"rating":5,"conditionType":0,"conditionParam1":0,"conditionParam2":0},{"skillId":171,"rating":6,"conditionType":1,"conditionParam1":2,"conditionParam2":4}],"battlerHue":0,"battlerName":"stone","dropItems":[{"kind":1,"dataId":364,"denominator":1},{"kind":1,"dataId":364,"denominator":1},{"dataId":1,"denominator":1,"kind":0}],"exp":1000,"traits":[{"code":22,"dataId":0,"value":0.95},{"code":31,"dataId":1,"value":0}],"gold":1000,"name":"Warped Crystal","note":"<BreakVal: 100>\n<BreakDuration: 3>","params":[500,0,40,60,6,6,24,1]},{"id":30,"actions":[{"conditionParam1":0,"conditionParam2":0,"conditionType":0,"rating":5,"skillId":1}],"battlerHue":0,"battlerName":"","dropItems":[{"dataId":1,"denominator":1,"kind":0},{"dataId":1,"denominator":1,"kind":0},{"dataId":1,"denominator":1,"kind":0}],"exp":0,"traits":[{"code":22,"dataId":0,"value":0.95},{"code":22,"dataId":1,"value":0.05},{"code":31,"dataId":1,"value":0}],"gold":0,"name":"","note":"","params":[100,0,10,10,10,10,10,10]},{"id":31,"actions":[{"skillId":1,"rating":1,"conditionType":0,"conditionParam1":0,"conditionParam2":0},{"skillId":179,"rating":7,"conditionType":6,"conditionParam1":590,"conditionParam2":0},{"skillId":180,"rating":8,"conditionType":6,"conditionParam1":590,"conditionParam2":0},{"skillId":181,"rating":9,"conditionType":6,"conditionParam1":591,"conditionParam2":0},{"skillId":183,"rating":9,"conditionType":6,"conditionParam1":592,"conditionParam2":0},{"skillId":184,"rating":6,"conditionType":6,"conditionParam1":594,"conditionParam2":0},{"skillId":181,"rating":6,"conditionType":6,"conditionParam1":595,"conditionParam2":0},{"skillId":185,"rating":6,"conditionType":6,"conditionParam1":596,"conditionParam2":0}],"battlerHue":0,"battlerName":"tenta01","dropItems":[{"dataId":1,"denominator":1,"kind":0},{"dataId":1,"denominator":1,"kind":0},{"dataId":1,"denominator":1,"kind":0}],"exp":640,"traits":[{"code":22,"dataId":0,"value":0.95},{"code":31,"dataId":1,"value":0}],"gold":200,"name":"Tentacle Swarm","note":"","params":[400,0,48,80,6,6,27,1]},{"id":32,"actions":[{"skillId":1,"rating":1,"conditionType":0,"conditionParam1":0,"conditionParam2":0},{"skillId":169,"rating":5,"conditionType":0,"conditionParam1":0,"conditionParam2":0},{"skillId":170,"rating":5,"conditionType":0,"conditionParam1":0,"conditionParam2":0},{"skillId":171,"rating":6,"conditionType":1,"conditionParam1":2,"conditionParam2":4}],"battlerHue":0,"battlerName":"doll_s2","dropItems":[{"kind":1,"dataId":354,"denominator":1},{"kind":1,"dataId":364,"denominator":1},{"kind":1,"dataId":373,"denominator":1}],"exp":520,"traits":[{"code":22,"dataId":0,"value":0.95},{"code":31,"dataId":1,"value":0}],"gold":188,"name":"Magic Doll Type-B","note":"<BreakVal: 200>\n<BreakDuration: 3>","params":[780,0,80,90,6,6,37,1]},{"id":33,"actions":[{"skillId":1,"rating":1,"conditionType":0,"conditionParam1":0,"conditionParam2":0},{"skillId":169,"rating":5,"conditionType":0,"conditionParam1":0,"conditionParam2":0},{"skillId":170,"rating":5,"conditionType":0,"conditionParam1":0,"conditionParam2":0},{"skillId":171,"rating":6,"conditionType":1,"conditionParam1":2,"conditionParam2":4}],"battlerHue":0,"battlerName":"doll_s3","dropItems":[{"kind":1,"dataId":364,"denominator":2},{"kind":1,"dataId":354,"denominator":2},{"dataId":1,"denominator":1,"kind":0}],"exp":680,"traits":[{"code":22,"dataId":0,"value":0.95},{"code":31,"dataId":1,"value":0}],"gold":230,"name":"Magic Doll Type-Q","note":"<BreakVal: 150>\n<BreakDuration: 5>","params":[800,0,80,90,6,6,37,1]},{"id":34,"actions":[{"skillId":1,"rating":1,"conditionType":0,"conditionParam1":0,"conditionParam2":0},{"skillId":169,"rating":5,"conditionType":0,"conditionParam1":0,"conditionParam2":0},{"skillId":170,"rating":5,"conditionType":0,"conditionParam1":0,"conditionParam2":0},{"skillId":171,"rating":6,"conditionType":1,"conditionParam1":2,"conditionParam2":4}],"battlerHue":0,"battlerName":"doll_s3s","dropItems":[{"kind":1,"dataId":364,"denominator":1},{"kind":1,"dataId":364,"denominator":2},{"dataId":1,"denominator":1,"kind":0}],"exp":1024,"traits":[{"code":22,"dataId":0,"value":0.95},{"code":31,"dataId":1,"value":0}],"gold":340,"name":"Magic Doll Type-K","note":"<BreakVal: 200>\n<BreakDuration: 4>","params":[800,0,90,100,6,6,37,1]},{"id":35,"actions":[{"skillId":1,"rating":1,"conditionType":0,"conditionParam1":0,"conditionParam2":0},{"skillId":102,"rating":4,"conditionType":0,"conditionParam1":0,"conditionParam2":0},{"skillId":170,"rating":5,"conditionType":0,"conditionParam1":0,"conditionParam2":0},{"skillId":171,"rating":6,"conditionType":1,"conditionParam1":2,"conditionParam2":4}],"battlerHue":0,"battlerName":"ad_golem4","dropItems":[{"kind":1,"dataId":372,"denominator":1},{"kind":0,"dataId":0,"denominator":1},{"dataId":1,"denominator":1,"kind":0}],"exp":2000,"traits":[{"code":22,"dataId":0,"value":0.9},{"code":31,"dataId":1,"value":0}],"gold":1500,"name":"Stone Magic Doll","note":"<BreakVal: 300>\n<BreakDuration: 5>","params":[1500,0,80,70,6,6,40,1]},{"id":36,"actions":[{"skillId":1,"rating":1,"conditionType":0,"conditionParam1":0,"conditionParam2":0},{"skillId":4,"rating":5,"conditionType":0,"conditionParam1":0,"conditionParam2":0}],"battlerHue":0,"battlerName":"cleaner","dropItems":[{"dataId":1,"denominator":1,"kind":0},{"dataId":1,"denominator":1,"kind":0},{"dataId":1,"denominator":1,"kind":0}],"exp":160,"traits":[{"code":22,"dataId":0,"value":0.95},{"code":31,"dataId":1,"value":0},{"code":11,"dataId":2,"value":1.5}],"gold":46,"name":"Mother Sucker","note":"","params":[280,0,43,26,6,6,38,1]},{"id":37,"actions":[{"skillId":1,"rating":1,"conditionType":0,"conditionParam1":0,"conditionParam2":0},{"skillId":177,"rating":5,"conditionType":0,"conditionParam1":0,"conditionParam2":0}],"battlerHue":0,"battlerName":"tenta01b","dropItems":[{"dataId":1,"denominator":1,"kind":0},{"dataId":1,"denominator":1,"kind":0},{"dataId":1,"denominator":1,"kind":0}],"exp":3000,"traits":[{"code":22,"dataId":0,"value":0.95},{"code":31,"dataId":1,"value":0}],"gold":2000,"name":"Milk Sucker Herd","note":"<BreakVal: 240>\n<BreakDuration: 6>","params":[1500,0,110,100,6,6,37,1]},{"id":38,"actions":[{"skillId":1,"rating":1,"conditionType":0,"conditionParam1":0,"conditionParam2":0},{"skillId":177,"rating":5,"conditionType":0,"conditionParam1":0,"conditionParam2":0}],"battlerHue":0,"battlerName":"tenta01b","dropItems":[{"dataId":1,"denominator":1,"kind":0},{"dataId":1,"denominator":1,"kind":0},{"dataId":1,"denominator":1,"kind":0}],"exp":840,"traits":[{"code":22,"dataId":0,"value":0.95},{"code":31,"dataId":1,"value":0}],"gold":366,"name":"Milk Sucker Herd","note":"<BreakVal: 120>\n<BreakDuration: 4>","params":[666,0,98,80,6,6,37,1]},{"id":39,"actions":[{"skillId":1,"rating":1,"conditionType":0,"conditionParam1":0,"conditionParam2":0},{"skillId":156,"rating":5,"conditionType":0,"conditionParam1":0,"conditionParam2":0},{"skillId":170,"rating":5,"conditionType":0,"conditionParam1":0,"conditionParam2":0},{"skillId":171,"rating":9,"conditionType":1,"conditionParam1":2,"conditionParam2":4},{"skillId":197,"rating":9,"conditionType":1,"conditionParam1":1,"conditionParam2":4}],"battlerHue":0,"battlerName":"ad_golem5","dropItems":[{"kind":1,"dataId":372,"denominator":1},{"kind":1,"dataId":364,"denominator":1},{"kind":1,"dataId":364,"denominator":1}],"exp":3100,"traits":[{"code":22,"dataId":0,"value":0.9},{"code":31,"dataId":1,"value":0}],"gold":2300,"name":"Stone Magic Doll","note":"<BreakVal: 600>\n<BreakDuration: 4>","params":[1500,0,90,100,6,6,28,1]},{"id":40,"actions":[{"skillId":1,"rating":1,"conditionType":0,"conditionParam1":0,"conditionParam2":0},{"skillId":196,"rating":5,"conditionType":0,"conditionParam1":0,"conditionParam2":0},{"skillId":188,"rating":5,"conditionType":0,"conditionParam1":0,"conditionParam2":0},{"skillId":195,"rating":5,"conditionType":0,"conditionParam1":0,"conditionParam2":0}],"battlerHue":0,"battlerName":"11_p","dropItems":[{"kind":0,"dataId":0,"denominator":1},{"kind":0,"dataId":0,"denominator":1},{"kind":0,"dataId":0,"denominator":1}],"exp":1300,"traits":[{"code":22,"dataId":0,"value":0.9},{"code":31,"dataId":1,"value":0}],"gold":680,"name":"Lake Tree","note":"<BreakVal: 350>\n<BreakDuration: 4>","params":[850,0,90,100,6,6,28,1]},{"id":41,"actions":[{"skillId":1,"rating":1,"conditionType":0,"conditionParam1":0,"conditionParam2":0},{"skillId":195,"rating":5,"conditionType":0,"conditionParam1":0,"conditionParam2":0},{"skillId":194,"rating":5,"conditionType":0,"conditionParam1":0,"conditionParam2":0},{"skillId":196,"rating":5,"conditionType":0,"conditionParam1":0,"conditionParam2":0},{"skillId":157,"rating":4,"conditionType":0,"conditionParam1":0,"conditionParam2":0}],"battlerHue":0,"battlerName":"12_p","dropItems":[{"kind":0,"dataId":0,"denominator":1},{"kind":0,"dataId":0,"denominator":1},{"kind":0,"dataId":0,"denominator":1}],"exp":3200,"traits":[{"code":22,"dataId":0,"value":0.9},{"code":31,"dataId":1,"value":0}],"gold":1200,"name":"Huge Lake Tree","note":"<BreakVal: 500>\n<BreakDuration: 4>","params":[1300,0,90,100,6,6,28,1]},{"id":42,"actions":[{"conditionParam1":0,"conditionParam2":0,"conditionType":0,"rating":5,"skillId":1}],"battlerHue":0,"battlerName":"","dropItems":[{"dataId":1,"denominator":1,"kind":0},{"dataId":1,"denominator":1,"kind":0},{"dataId":1,"denominator":1,"kind":0}],"exp":0,"traits":[{"code":22,"dataId":0,"value":0.95},{"code":22,"dataId":1,"value":0.05},{"code":31,"dataId":1,"value":0}],"gold":0,"name":"","note":"","params":[100,0,10,10,10,10,10,10]},{"id":43,"actions":[{"conditionParam1":0,"conditionParam2":0,"conditionType":0,"rating":5,"skillId":1}],"battlerHue":0,"battlerName":"","dropItems":[{"dataId":1,"denominator":1,"kind":0},{"dataId":1,"denominator":1,"kind":0},{"dataId":1,"denominator":1,"kind":0}],"exp":0,"traits":[{"code":22,"dataId":0,"value":0.95},{"code":22,"dataId":1,"value":0.05},{"code":31,"dataId":1,"value":0}],"gold":0,"name":"","note":"","params":[100,0,10,10,10,10,10,10]},{"id":44,"actions":[{"conditionParam1":0,"conditionParam2":0,"conditionType":0,"rating":5,"skillId":1}],"battlerHue":0,"battlerName":"","dropItems":[{"dataId":1,"denominator":1,"kind":0},{"dataId":1,"denominator":1,"kind":0},{"dataId":1,"denominator":1,"kind":0}],"exp":0,"traits":[{"code":22,"dataId":0,"value":0.95},{"code":22,"dataId":1,"value":0.05},{"code":31,"dataId":1,"value":0}],"gold":0,"name":"","note":"","params":[100,0,10,10,10,10,10,10]},{"id":45,"actions":[{"skillId":1,"rating":1,"conditionType":0,"conditionParam1":0,"conditionParam2":0},{"skillId":199,"rating":5,"conditionType":0,"conditionParam1":0,"conditionParam2":0},{"skillId":200,"rating":5,"conditionType":0,"conditionParam1":0,"conditionParam2":0},{"skillId":188,"rating":5,"conditionType":0,"conditionParam1":0,"conditionParam2":0},{"skillId":201,"rating":9,"conditionType":1,"conditionParam1":3,"conditionParam2":0},{"skillId":202,"rating":9,"conditionType":1,"conditionParam1":6,"conditionParam2":0}],"battlerHue":0,"battlerName":"darkfantasy-flayer","dropItems":[{"kind":0,"dataId":0,"denominator":1},{"kind":0,"dataId":0,"denominator":1},{"dataId":1,"denominator":1,"kind":0}],"exp":3888,"traits":[{"code":22,"dataId":0,"value":0.95},{"code":31,"dataId":1,"value":0}],"gold":7500,"name":"Hooded Man","note":"","params":[1000,0,70,130,6,6,63,1]},{"id":46,"actions":[{"skillId":1,"rating":1,"conditionType":0,"conditionParam1":0,"conditionParam2":0},{"skillId":157,"rating":5,"conditionType":1,"conditionParam1":1,"conditionParam2":4},{"skillId":190,"rating":5,"conditionType":1,"conditionParam1":3,"conditionParam2":4},{"skillId":203,"rating":5,"conditionType":1,"conditionParam1":4,"conditionParam2":4},{"skillId":156,"rating":5,"conditionType":1,"conditionParam1":2,"conditionParam2":4}],"battlerHue":0,"battlerName":"SF_MechasphereWH","dropItems":[{"kind":1,"dataId":372,"denominator":1},{"kind":0,"dataId":0,"denominator":1},{"dataId":1,"denominator":1,"kind":0}],"exp":2900,"traits":[{"code":22,"dataId":0,"value":0.95},{"code":31,"dataId":1,"value":0}],"gold":1050,"name":"White Bit","note":"<BreakVal: 1000>\n<BreakDuration: 7>","params":[1000,0,90,100,6,6,52,1]},{"id":47,"actions":[{"skillId":1,"rating":1,"conditionType":0,"conditionParam1":0,"conditionParam2":0},{"skillId":169,"rating":5,"conditionType":1,"conditionParam1":4,"conditionParam2":4},{"skillId":156,"rating":5,"conditionType":1,"conditionParam1":2,"conditionParam2":4},{"skillId":159,"rating":5,"conditionType":1,"conditionParam1":3,"conditionParam2":4},{"skillId":157,"rating":5,"conditionType":1,"conditionParam1":1,"conditionParam2":4}],"battlerHue":0,"battlerName":"SF_MechasphereBL","dropItems":[{"kind":1,"dataId":372,"denominator":1},{"kind":0,"dataId":0,"denominator":1},{"dataId":1,"denominator":1,"kind":0}],"exp":2900,"traits":[{"code":22,"dataId":0,"value":0.95},{"code":31,"dataId":1,"value":0}],"gold":1050,"name":"Black Bit","note":"<BreakVal: 500>\n<BreakDuration: 7>","params":[1000,0,120,80,6,6,48,1]},{"id":48,"actions":[{"skillId":1,"rating":1,"conditionType":0,"conditionParam1":0,"conditionParam2":0},{"skillId":187,"rating":4,"conditionType":1,"conditionParam1":1,"conditionParam2":7},{"skillId":188,"rating":4,"conditionType":1,"conditionParam1":2,"conditionParam2":7},{"skillId":189,"rating":4,"conditionType":1,"conditionParam1":3,"conditionParam2":7},{"skillId":190,"rating":4,"conditionType":1,"conditionParam1":4,"conditionParam2":7},{"skillId":191,"rating":4,"conditionType":1,"conditionParam1":5,"conditionParam2":7},{"skillId":192,"rating":4,"conditionType":1,"conditionParam1":6,"conditionParam2":7}],"battlerHue":0,"battlerName":"Guardian_F_BIG","dropItems":[{"kind":0,"dataId":0,"denominator":1},{"kind":0,"dataId":0,"denominator":1},{"dataId":1,"denominator":1,"kind":0}],"exp":5006,"traits":[{"code":22,"dataId":0,"value":0.95},{"code":31,"dataId":1,"value":0}],"gold":5006,"name":"Scrapped Golem","note":"<BreakVal: 1000>\n<BreakDuration: 7>","params":[3500,0,130,160,6,6,65,1]},{"id":49,"actions":[{"conditionParam1":0,"conditionParam2":0,"conditionType":0,"rating":5,"skillId":1}],"battlerHue":0,"battlerName":"","dropItems":[{"dataId":1,"denominator":1,"kind":0},{"dataId":1,"denominator":1,"kind":0},{"dataId":1,"denominator":1,"kind":0}],"exp":0,"traits":[{"code":22,"dataId":0,"value":0.95},{"code":22,"dataId":1,"value":0.05},{"code":31,"dataId":1,"value":0}],"gold":0,"name":"","note":"","params":[100,0,10,10,10,10,10,10]},{"id":50,"actions":[{"conditionParam1":0,"conditionParam2":0,"conditionType":0,"rating":5,"skillId":1}],"battlerHue":0,"battlerName":"","dropItems":[{"dataId":1,"denominator":1,"kind":0},{"dataId":1,"denominator":1,"kind":0},{"dataId":1,"denominator":1,"kind":0}],"exp":0,"traits":[{"code":22,"dataId":0,"value":0.95},{"code":22,"dataId":1,"value":0.05},{"code":31,"dataId":1,"value":0}],"gold":0,"name":"","note":"","params":[100,0,10,10,10,10,10,10]}]